{
  "benchmark_name": "Single-Threaded Performance",
  "total_operations": 75,
  "successful_operations": 70,
  "failed_operations": 5,
  "average_execution_time": 0.008993118149893625,
  "median_execution_time": 0.007000923156738281,
  "p95_execution_time": 0.013713788986206054,
  "p99_execution_time": 0.020651621818542493,
  "throughput_ops_per_second": 111.196137238765,
  "memory_peak_mb": 0.97265625,
  "cpu_peak_percent": 0.0,
  "cache_hit_rate": 0.0,
  "parallel_efficiency": 1.0,
  "workload_balance": 1.0,
  "detailed_metrics": [
    {
      "operation": "verify_ttest",
      "test_type": "ttest",
      "data_size": 1000,
      "execution_time": 0.024415254592895508,
      "memory_usage": 0.97265625,
      "cpu_usage": 0.0,
      "success": true,
      "error_message": null,
      "cache_hit": false,
      "parallel_workers": 1,
      "parallel_efficiency": 1.0,
      "workload_balance": 1.0
    },
    {
      "operation": "verify_ttest",
      "test_type": "ttest",
      "data_size": 1000,
      "execution_time": 0.01255345344543457,
      "memory_usage": 0.140625,
      "cpu_usage": 0.0,
      "success": true,
      "error_message": null,
      "cache_hit": false,
      "parallel_workers": 1,
      "parallel_efficiency": 1.0,
      "workload_balance": 1.0
    },
    {
      "operation": "verify_ttest",
      "test_type": "ttest",
      "data_size": 1000,
      "execution_time": 0.012080192565917969,
      "memory_usage": 0.0625,
      "cpu_usage": 0.0,
      "success": true,
      "error_message": null,
      "cache_hit": false,
      "parallel_workers": 1,
      "parallel_efficiency": 1.0,
      "workload_balance": 1.0
    },
    {
      "operation": "verify_ttest",
      "test_type": "ttest",
      "data_size": 1000,
      "execution_time": 0.01300048828125,
      "memory_usage": 0.00390625,
      "cpu_usage": 0.0,
      "success": true,
      "error_message": null,
      "cache_hit": false,
      "parallel_workers": 1,
      "parallel_efficiency": 1.0,
      "workload_balance": 1.0
    },
    {
      "operation": "verify_ttest",
      "test_type": "ttest",
      "data_size": 1000,
      "execution_time": 0.011337757110595703,
      "memory_usage": 0,
      "cpu_usage": 0.0,
      "success": true,
      "error_message": null,
      "cache_hit": false,
      "parallel_workers": 1,
      "parallel_efficiency": 1.0,
      "workload_balance": 1.0
    },
    {
      "operation": "verify_anova",
      "test_type": "anova",
      "data_size": 1000,
      "execution_time": 0.024135351181030273,
      "memory_usage": 0.26953125,
      "cpu_usage": 0.0,
      "success": false,
      "error_message": null,
      "cache_hit": false,
      "parallel_workers": 1,
      "parallel_efficiency": 1.0,
      "workload_balance": 1.0
    },
    {
      "operation": "verify_anova",
      "test_type": "anova",
      "data_size": 1000,
      "execution_time": 0.01943230628967285,
      "memory_usage": 0,
      "cpu_usage": 0.0,
      "success": false,
      "error_message": null,
      "cache_hit": false,
      "parallel_workers": 1,
      "parallel_efficiency": 1.0,
      "workload_balance": 1.0
    },
    {
      "operation": "verify_anova",
      "test_type": "anova",
      "data_size": 1000,
      "execution_time": 0.016992807388305664,
      "memory_usage": 0,
      "cpu_usage": 0.0,
      "success": false,
      "error_message": null,
      "cache_hit": false,
      "parallel_workers": 1,
      "parallel_efficiency": 1.0,
      "workload_balance": 1.0
    },
    {
      "operation": "verify_anova",
      "test_type": "anova",
      "data_size": 1000,
      "execution_time": 0.016815662384033203,
      "memory_usage": 0,
      "cpu_usage": 0.0,
      "success": false,
      "error_message": null,
      "cache_hit": false,
      "parallel_workers": 1,
      "parallel_efficiency": 1.0,
      "workload_balance": 1.0
    },
    {
      "operation": "verify_anova",
      "test_type": "anova",
      "data_size": 1000,
      "execution_time": 0.017336130142211914,
      "memory_usage": 0,
      "cpu_usage": 0.0,
      "success": false,
      "error_message": null,
      "cache_hit": false,
      "parallel_workers": 1,
      "parallel_efficiency": 1.0,
      "workload_balance": 1.0
    },
    {
      "operation": "verify_chi2",
      "test_type": "chi2",
      "data_size": 1000,
      "execution_time": 0.011358976364135742,
      "memory_usage": 0.11328125,
      "cpu_usage": 0.0,
      "success": true,
      "error_message": null,
      "cache_hit": false,
      "parallel_workers": 1,
      "parallel_efficiency": 1.0,
      "workload_balance": 1.0
    },
    {
      "operation": "verify_chi2",
      "test_type": "chi2",
      "data_size": 1000,
      "execution_time": 0.005026817321777344,
      "memory_usage": 0.05859375,
      "cpu_usage": 0.0,
      "success": true,
      "error_message": null,
      "cache_hit": false,
      "parallel_workers": 1,
      "parallel_efficiency": 1.0,
      "workload_balance": 1.0
    },
    {
      "operation": "verify_chi2",
      "test_type": "chi2",
      "data_size": 1000,
      "execution_time": 0.004522085189819336,
      "memory_usage": 0,
      "cpu_usage": 0.0,
      "success": true,
      "error_message": null,
      "cache_hit": false,
      "parallel_workers": 1,
      "parallel_efficiency": 1.0,
      "workload_balance": 1.0
    },
    {
      "operation": "verify_chi2",
      "test_type": "chi2",
      "data_size": 1000,
      "execution_time": 0.004448890686035156,
      "memory_usage": 0,
      "cpu_usage": 0.0,
      "success": true,
      "error_message": null,
      "cache_hit": false,
      "parallel_workers": 1,
      "parallel_efficiency": 1.0,
      "workload_balance": 1.0
    },
    {
      "operation": "verify_chi2",
      "test_type": "chi2",
      "data_size": 1000,
      "execution_time": 0.006215095520019531,
      "memory_usage": 0,
      "cpu_usage": 0.0,
      "success": true,
      "error_message": null,
      "cache_hit": false,
      "parallel_workers": 1,
      "parallel_efficiency": 1.0,
      "workload_balance": 1.0
    },
    {
      "operation": "verify_wilcoxon",
      "test_type": "wilcoxon",
      "data_size": 1000,
      "execution_time": 0.01896071434020996,
      "memory_usage": 0.1953125,
      "cpu_usage": 0.0,
      "success": true,
      "error_message": null,
      "cache_hit": false,
      "parallel_workers": 1,
      "parallel_efficiency": 1.0,
      "workload_balance": 1.0
    },
    {
      "operation": "verify_wilcoxon",
      "test_type": "wilcoxon",
      "data_size": 1000,
      "execution_time": 0.01185154914855957,
      "memory_usage": 0.08984375,
      "cpu_usage": 0.0,
      "success": true,
      "error_message": null,
      "cache_hit": false,
      "parallel_workers": 1,
      "parallel_efficiency": 1.0,
      "workload_balance": 1.0
    },
    {
      "operation": "verify_wilcoxon",
      "test_type": "wilcoxon",
      "data_size": 1000,
      "execution_time": 0.012012481689453125,
      "memory_usage": 0,
      "cpu_usage": 0.0,
      "success": true,
      "error_message": null,
      "cache_hit": false,
      "parallel_workers": 1,
      "parallel_efficiency": 1.0,
      "workload_balance": 1.0
    },
    {
      "operation": "verify_wilcoxon",
      "test_type": "wilcoxon",
      "data_size": 1000,
      "execution_time": 0.011772871017456055,
      "memory_usage": 0,
      "cpu_usage": 0.0,
      "success": true,
      "error_message": null,
      "cache_hit": false,
      "parallel_workers": 1,
      "parallel_efficiency": 1.0,
      "workload_balance": 1.0
    },
    {
      "operation": "verify_wilcoxon",
      "test_type": "wilcoxon",
      "data_size": 1000,
      "execution_time": 0.013431549072265625,
      "memory_usage": 0,
      "cpu_usage": 0.0,
      "success": true,
      "error_message": null,
      "cache_hit": false,
      "parallel_workers": 1,
      "parallel_efficiency": 1.0,
      "workload_balance": 1.0
    },
    {
      "operation": "verify_mann-whitney",
      "test_type": "mann-whitney",
      "data_size": 1000,
      "execution_time": 0.017867088317871094,
      "memory_usage": 0.16796875,
      "cpu_usage": 0.0,
      "success": true,
      "error_message": null,
      "cache_hit": false,
      "parallel_workers": 1,
      "parallel_efficiency": 1.0,
      "workload_balance": 1.0
    },
    {
      "operation": "verify_mann-whitney",
      "test_type": "mann-whitney",
      "data_size": 1000,
      "execution_time": 0.01192927360534668,
      "memory_usage": 0.08984375,
      "cpu_usage": 0.0,
      "success": true,
      "error_message": null,
      "cache_hit": false,
      "parallel_workers": 1,
      "parallel_efficiency": 1.0,
      "workload_balance": 1.0
    },
    {
      "operation": "verify_mann-whitney",
      "test_type": "mann-whitney",
      "data_size": 1000,
      "execution_time": 0.012595176696777344,
      "memory_usage": 0,
      "cpu_usage": 0.0,
      "success": true,
      "error_message": null,
      "cache_hit": false,
      "parallel_workers": 1,
      "parallel_efficiency": 1.0,
      "workload_balance": 1.0
    },
    {
      "operation": "verify_mann-whitney",
      "test_type": "mann-whitney",
      "data_size": 1000,
      "execution_time": 0.012185335159301758,
      "memory_usage": 0,
      "cpu_usage": 0.0,
      "success": true,
      "error_message": null,
      "cache_hit": false,
      "parallel_workers": 1,
      "parallel_efficiency": 1.0,
      "workload_balance": 1.0
    },
    {
      "operation": "verify_mann-whitney",
      "test_type": "mann-whitney",
      "data_size": 1000,
      "execution_time": 0.011575460433959961,
      "memory_usage": 0,
      "cpu_usage": 0.0,
      "success": true,
      "error_message": null,
      "cache_hit": false,
      "parallel_workers": 1,
      "parallel_efficiency": 1.0,
      "workload_balance": 1.0
    },
    {
      "operation": "verify_kruskal",
      "test_type": "kruskal",
      "data_size": 1000,
      "execution_time": 0.01206517219543457,
      "memory_usage": 0.171875,
      "cpu_usage": 0.0,
      "success": true,
      "error_message": null,
      "cache_hit": false,
      "parallel_workers": 1,
      "parallel_efficiency": 1.0,
      "workload_balance": 1.0
    },
    {
      "operation": "verify_kruskal",
      "test_type": "kruskal",
      "data_size": 1000,
      "execution_time": 0.007717609405517578,
      "memory_usage": 0.04296875,
      "cpu_usage": 0.0,
      "success": true,
      "error_message": null,
      "cache_hit": false,
      "parallel_workers": 1,
      "parallel_efficiency": 1.0,
      "workload_balance": 1.0
    },
    {
      "operation": "verify_kruskal",
      "test_type": "kruskal",
      "data_size": 1000,
      "execution_time": 0.00599217414855957,
      "memory_usage": 0,
      "cpu_usage": 0.0,
      "success": true,
      "error_message": null,
      "cache_hit": false,
      "parallel_workers": 1,
      "parallel_efficiency": 1.0,
      "workload_balance": 1.0
    },
    {
      "operation": "verify_kruskal",
      "test_type": "kruskal",
      "data_size": 1000,
      "execution_time": 0.007520437240600586,
      "memory_usage": 0,
      "cpu_usage": 0.0,
      "success": true,
      "error_message": null,
      "cache_hit": false,
      "parallel_workers": 1,
      "parallel_efficiency": 1.0,
      "workload_balance": 1.0
    },
    {
      "operation": "verify_kruskal",
      "test_type": "kruskal",
      "data_size": 1000,
      "execution_time": 0.006519794464111328,
      "memory_usage": 0,
      "cpu_usage": 0.0,
      "success": true,
      "error_message": null,
      "cache_hit": false,
      "parallel_workers": 1,
      "parallel_efficiency": 1.0,
      "workload_balance": 1.0
    },
    {
      "operation": "verify_bartlett",
      "test_type": "bartlett",
      "data_size": 1000,
      "execution_time": 0.013818502426147461,
      "memory_usage": 0.20703125,
      "cpu_usage": 0.0,
      "success": true,
      "error_message": null,
      "cache_hit": false,
      "parallel_workers": 1,
      "parallel_efficiency": 1.0,
      "workload_balance": 1.0
    },
    {
      "operation": "verify_bartlett",
      "test_type": "bartlett",
      "data_size": 1000,
      "execution_time": 0.00666046142578125,
      "memory_usage": 0.04296875,
      "cpu_usage": 0.0,
      "success": true,
      "error_message": null,
      "cache_hit": false,
      "parallel_workers": 1,
      "parallel_efficiency": 1.0,
      "workload_balance": 1.0
    },
    {
      "operation": "verify_bartlett",
      "test_type": "bartlett",
      "data_size": 1000,
      "execution_time": 0.007312297821044922,
      "memory_usage": 0,
      "cpu_usage": 0.0,
      "success": true,
      "error_message": null,
      "cache_hit": false,
      "parallel_workers": 1,
      "parallel_efficiency": 1.0,
      "workload_balance": 1.0
    },
    {
      "operation": "verify_bartlett",
      "test_type": "bartlett",
      "data_size": 1000,
      "execution_time": 0.006913900375366211,
      "memory_usage": 0,
      "cpu_usage": 0.0,
      "success": true,
      "error_message": null,
      "cache_hit": false,
      "parallel_workers": 1,
      "parallel_efficiency": 1.0,
      "workload_balance": 1.0
    },
    {
      "operation": "verify_bartlett",
      "test_type": "bartlett",
      "data_size": 1000,
      "execution_time": 0.00673222541809082,
      "memory_usage": 0,
      "cpu_usage": 0.0,
      "success": true,
      "error_message": null,
      "cache_hit": false,
      "parallel_workers": 1,
      "parallel_efficiency": 1.0,
      "workload_balance": 1.0
    },
    {
      "operation": "verify_fligner",
      "test_type": "fligner",
      "data_size": 1000,
      "execution_time": 0.01183009147644043,
      "memory_usage": 0.23828125,
      "cpu_usage": 0.0,
      "success": true,
      "error_message": null,
      "cache_hit": false,
      "parallel_workers": 1,
      "parallel_efficiency": 1.0,
      "workload_balance": 1.0
    },
    {
      "operation": "verify_fligner",
      "test_type": "fligner",
      "data_size": 1000,
      "execution_time": 0.006654500961303711,
      "memory_usage": 0.05859375,
      "cpu_usage": 0.0,
      "success": true,
      "error_message": null,
      "cache_hit": false,
      "parallel_workers": 1,
      "parallel_efficiency": 1.0,
      "workload_balance": 1.0
    },
    {
      "operation": "verify_fligner",
      "test_type": "fligner",
      "data_size": 1000,
      "execution_time": 0.00599980354309082,
      "memory_usage": 0.00390625,
      "cpu_usage": 0.0,
      "success": true,
      "error_message": null,
      "cache_hit": false,
      "parallel_workers": 1,
      "parallel_efficiency": 1.0,
      "workload_balance": 1.0
    },
    {
      "operation": "verify_fligner",
      "test_type": "fligner",
      "data_size": 1000,
      "execution_time": 0.006308555603027344,
      "memory_usage": 0,
      "cpu_usage": 0.0,
      "success": true,
      "error_message": null,
      "cache_hit": false,
      "parallel_workers": 1,
      "parallel_efficiency": 1.0,
      "workload_balance": 1.0
    },
    {
      "operation": "verify_fligner",
      "test_type": "fligner",
      "data_size": 1000,
      "execution_time": 0.006508588790893555,
      "memory_usage": 0,
      "cpu_usage": 0.0,
      "success": true,
      "error_message": null,
      "cache_hit": false,
      "parallel_workers": 1,
      "parallel_efficiency": 1.0,
      "workload_balance": 1.0
    },
    {
      "operation": "verify_dunnett",
      "test_type": "dunnett",
      "data_size": 1000,
      "execution_time": 0.013585805892944336,
      "memory_usage": 0.203125,
      "cpu_usage": 0.0,
      "success": true,
      "error_message": null,
      "cache_hit": false,
      "parallel_workers": 1,
      "parallel_efficiency": 1.0,
      "workload_balance": 1.0
    },
    {
      "operation": "verify_dunnett",
      "test_type": "dunnett",
      "data_size": 1000,
      "execution_time": 0.006685018539428711,
      "memory_usage": 0.06640625,
      "cpu_usage": 0.0,
      "success": true,
      "error_message": null,
      "cache_hit": false,
      "parallel_workers": 1,
      "parallel_efficiency": 1.0,
      "workload_balance": 1.0
    },
    {
      "operation": "verify_dunnett",
      "test_type": "dunnett",
      "data_size": 1000,
      "execution_time": 0.006003618240356445,
      "memory_usage": 0,
      "cpu_usage": 0.0,
      "success": true,
      "error_message": null,
      "cache_hit": false,
      "parallel_workers": 1,
      "parallel_efficiency": 1.0,
      "workload_balance": 1.0
    },
    {
      "operation": "verify_dunnett",
      "test_type": "dunnett",
      "data_size": 1000,
      "execution_time": 0.006088972091674805,
      "memory_usage": 0,
      "cpu_usage": 0.0,
      "success": true,
      "error_message": null,
      "cache_hit": false,
      "parallel_workers": 1,
      "parallel_efficiency": 1.0,
      "workload_balance": 1.0
    },
    {
      "operation": "verify_dunnett",
      "test_type": "dunnett",
      "data_size": 1000,
      "execution_time": 0.008335113525390625,
      "memory_usage": 0,
      "cpu_usage": 0.0,
      "success": true,
      "error_message": null,
      "cache_hit": false,
      "parallel_workers": 1,
      "parallel_efficiency": 1.0,
      "workload_balance": 1.0
    },
    {
      "operation": "verify_tukey",
      "test_type": "tukey",
      "data_size": 1000,
      "execution_time": 0.011536121368408203,
      "memory_usage": 0.00390625,
      "cpu_usage": 0.0,
      "success": true,
      "error_message": null,
      "cache_hit": false,
      "parallel_workers": 1,
      "parallel_efficiency": 1.0,
      "workload_balance": 1.0
    },
    {
      "operation": "verify_tukey",
      "test_type": "tukey",
      "data_size": 1000,
      "execution_time": 0.0074656009674072266,
      "memory_usage": 0.00390625,
      "cpu_usage": 0.0,
      "success": true,
      "error_message": null,
      "cache_hit": false,
      "parallel_workers": 1,
      "parallel_efficiency": 1.0,
      "workload_balance": 1.0
    },
    {
      "operation": "verify_tukey",
      "test_type": "tukey",
      "data_size": 1000,
      "execution_time": 0.00699925422668457,
      "memory_usage": 0,
      "cpu_usage": 0.0,
      "success": true,
      "error_message": null,
      "cache_hit": false,
      "parallel_workers": 1,
      "parallel_efficiency": 1.0,
      "workload_balance": 1.0
    },
    {
      "operation": "verify_tukey",
      "test_type": "tukey",
      "data_size": 1000,
      "execution_time": 0.006453037261962891,
      "memory_usage": 0,
      "cpu_usage": 0.0,
      "success": true,
      "error_message": null,
      "cache_hit": false,
      "parallel_workers": 1,
      "parallel_efficiency": 1.0,
      "workload_balance": 1.0
    },
    {
      "operation": "verify_tukey",
      "test_type": "tukey",
      "data_size": 1000,
      "execution_time": 0.008176565170288086,
      "memory_usage": 0,
      "cpu_usage": 0.0,
      "success": true,
      "error_message": null,
      "cache_hit": false,
      "parallel_workers": 1,
      "parallel_efficiency": 1.0,
      "workload_balance": 1.0
    },
    {
      "operation": "verify_steel",
      "test_type": "steel",
      "data_size": 1000,
      "execution_time": 0.011610031127929688,
      "memory_usage": 0.00390625,
      "cpu_usage": 0.0,
      "success": true,
      "error_message": null,
      "cache_hit": false,
      "parallel_workers": 1,
      "parallel_efficiency": 1.0,
      "workload_balance": 1.0
    },
    {
      "operation": "verify_steel",
      "test_type": "steel",
      "data_size": 1000,
      "execution_time": 0.006005764007568359,
      "memory_usage": 0.00390625,
      "cpu_usage": 0.0,
      "success": true,
      "error_message": null,
      "cache_hit": false,
      "parallel_workers": 1,
      "parallel_efficiency": 1.0,
      "workload_balance": 1.0
    },
    {
      "operation": "verify_steel",
      "test_type": "steel",
      "data_size": 1000,
      "execution_time": 0.005769014358520508,
      "memory_usage": 0,
      "cpu_usage": 0.0,
      "success": true,
      "error_message": null,
      "cache_hit": false,
      "parallel_workers": 1,
      "parallel_efficiency": 1.0,
      "workload_balance": 1.0
    },
    {
      "operation": "verify_steel",
      "test_type": "steel",
      "data_size": 1000,
      "execution_time": 0.007002115249633789,
      "memory_usage": 0,
      "cpu_usage": 0.0,
      "success": true,
      "error_message": null,
      "cache_hit": false,
      "parallel_workers": 1,
      "parallel_efficiency": 1.0,
      "workload_balance": 1.0
    },
    {
      "operation": "verify_steel",
      "test_type": "steel",
      "data_size": 1000,
      "execution_time": 0.006994724273681641,
      "memory_usage": 0,
      "cpu_usage": 0.0,
      "success": true,
      "error_message": null,
      "cache_hit": false,
      "parallel_workers": 1,
      "parallel_efficiency": 1.0,
      "workload_balance": 1.0
    },
    {
      "operation": "verify_steel-dwass",
      "test_type": "steel-dwass",
      "data_size": 1000,
      "execution_time": 0.012042522430419922,
      "memory_usage": 0.0078125,
      "cpu_usage": 0.0,
      "success": true,
      "error_message": null,
      "cache_hit": false,
      "parallel_workers": 1,
      "parallel_efficiency": 1.0,
      "workload_balance": 1.0
    },
    {
      "operation": "verify_steel-dwass",
      "test_type": "steel-dwass",
      "data_size": 1000,
      "execution_time": 0.0059969425201416016,
      "memory_usage": 0,
      "cpu_usage": 0.0,
      "success": true,
      "error_message": null,
      "cache_hit": false,
      "parallel_workers": 1,
      "parallel_efficiency": 1.0,
      "workload_balance": 1.0
    },
    {
      "operation": "verify_steel-dwass",
      "test_type": "steel-dwass",
      "data_size": 1000,
      "execution_time": 0.006716012954711914,
      "memory_usage": 0,
      "cpu_usage": 0.0,
      "success": true,
      "error_message": null,
      "cache_hit": false,
      "parallel_workers": 1,
      "parallel_efficiency": 1.0,
      "workload_balance": 1.0
    },
    {
      "operation": "verify_steel-dwass",
      "test_type": "steel-dwass",
      "data_size": 1000,
      "execution_time": 0.006462812423706055,
      "memory_usage": 0,
      "cpu_usage": 0.0,
      "success": true,
      "error_message": null,
      "cache_hit": false,
      "parallel_workers": 1,
      "parallel_efficiency": 1.0,
      "workload_balance": 1.0
    },
    {
      "operation": "verify_steel-dwass",
      "test_type": "steel-dwass",
      "data_size": 1000,
      "execution_time": 0.006266355514526367,
      "memory_usage": 0,
      "cpu_usage": 0.0,
      "success": true,
      "error_message": null,
      "cache_hit": false,
      "parallel_workers": 1,
      "parallel_efficiency": 1.0,
      "workload_balance": 1.0
    },
    {
      "operation": "verify_williams",
      "test_type": "williams",
      "data_size": 1000,
      "execution_time": 0.012001514434814453,
      "memory_usage": 0.01171875,
      "cpu_usage": 0.0,
      "success": true,
      "error_message": null,
      "cache_hit": false,
      "parallel_workers": 1,
      "parallel_efficiency": 1.0,
      "workload_balance": 1.0
    },
    {
      "operation": "verify_williams",
      "test_type": "williams",
      "data_size": 1000,
      "execution_time": 0.0065305233001708984,
      "memory_usage": 0.00390625,
      "cpu_usage": 0.0,
      "success": true,
      "error_message": null,
      "cache_hit": false,
      "parallel_workers": 1,
      "parallel_efficiency": 1.0,
      "workload_balance": 1.0
    },
    {
      "operation": "verify_williams",
      "test_type": "williams",
      "data_size": 1000,
      "execution_time": 0.0069997310638427734,
      "memory_usage": 0,
      "cpu_usage": 0.0,
      "success": true,
      "error_message": null,
      "cache_hit": false,
      "parallel_workers": 1,
      "parallel_efficiency": 1.0,
      "workload_balance": 1.0
    },
    {
      "operation": "verify_williams",
      "test_type": "williams",
      "data_size": 1000,
      "execution_time": 0.006677150726318359,
      "memory_usage": 0,
      "cpu_usage": 0.0,
      "success": true,
      "error_message": null,
      "cache_hit": false,
      "parallel_workers": 1,
      "parallel_efficiency": 1.0,
      "workload_balance": 1.0
    },
    {
      "operation": "verify_williams",
      "test_type": "williams",
      "data_size": 1000,
      "execution_time": 0.006513357162475586,
      "memory_usage": 0,
      "cpu_usage": 0.0,
      "success": true,
      "error_message": null,
      "cache_hit": false,
      "parallel_workers": 1,
      "parallel_efficiency": 1.0,
      "workload_balance": 1.0
    },
    {
      "operation": "verify_poisson",
      "test_type": "poisson",
      "data_size": 1000,
      "execution_time": 0.011921882629394531,
      "memory_usage": 0,
      "cpu_usage": 0.0,
      "success": true,
      "error_message": null,
      "cache_hit": false,
      "parallel_workers": 1,
      "parallel_efficiency": 1.0,
      "workload_balance": 1.0
    },
    {
      "operation": "verify_poisson",
      "test_type": "poisson",
      "data_size": 1000,
      "execution_time": 0.005951404571533203,
      "memory_usage": 0,
      "cpu_usage": 0.0,
      "success": true,
      "error_message": null,
      "cache_hit": false,
      "parallel_workers": 1,
      "parallel_efficiency": 1.0,
      "workload_balance": 1.0
    },
    {
      "operation": "verify_poisson",
      "test_type": "poisson",
      "data_size": 1000,
      "execution_time": 0.00620722770690918,
      "memory_usage": 0,
      "cpu_usage": 0.0,
      "success": true,
      "error_message": null,
      "cache_hit": false,
      "parallel_workers": 1,
      "parallel_efficiency": 1.0,
      "workload_balance": 1.0
    },
    {
      "operation": "verify_poisson",
      "test_type": "poisson",
      "data_size": 1000,
      "execution_time": 0.007010698318481445,
      "memory_usage": 0,
      "cpu_usage": 0.0,
      "success": true,
      "error_message": null,
      "cache_hit": false,
      "parallel_workers": 1,
      "parallel_efficiency": 1.0,
      "workload_balance": 1.0
    },
    {
      "operation": "verify_poisson",
      "test_type": "poisson",
      "data_size": 1000,
      "execution_time": 0.006674766540527344,
      "memory_usage": 0,
      "cpu_usage": 0.0,
      "success": true,
      "error_message": null,
      "cache_hit": false,
      "parallel_workers": 1,
      "parallel_efficiency": 1.0,
      "workload_balance": 1.0
    },
    {
      "operation": "verify_binom",
      "test_type": "binom",
      "data_size": 1000,
      "execution_time": 0.011495351791381836,
      "memory_usage": 0.00390625,
      "cpu_usage": 0.0,
      "success": true,
      "error_message": null,
      "cache_hit": false,
      "parallel_workers": 1,
      "parallel_efficiency": 1.0,
      "workload_balance": 1.0
    },
    {
      "operation": "verify_binom",
      "test_type": "binom",
      "data_size": 1000,
      "execution_time": 0.006803750991821289,
      "memory_usage": 0,
      "cpu_usage": 0.0,
      "success": true,
      "error_message": null,
      "cache_hit": false,
      "parallel_workers": 1,
      "parallel_efficiency": 1.0,
      "workload_balance": 1.0
    },
    {
      "operation": "verify_binom",
      "test_type": "binom",
      "data_size": 1000,
      "execution_time": 0.007485628128051758,
      "memory_usage": 0,
      "cpu_usage": 0.0,
      "success": true,
      "error_message": null,
      "cache_hit": false,
      "parallel_workers": 1,
      "parallel_efficiency": 1.0,
      "workload_balance": 1.0
    },
    {
      "operation": "verify_binom",
      "test_type": "binom",
      "data_size": 1000,
      "execution_time": 0.006871461868286133,
      "memory_usage": 0,
      "cpu_usage": 0.0,
      "success": true,
      "error_message": null,
      "cache_hit": false,
      "parallel_workers": 1,
      "parallel_efficiency": 1.0,
      "workload_balance": 1.0
    },
    {
      "operation": "verify_binom",
      "test_type": "binom",
      "data_size": 1000,
      "execution_time": 0.006483793258666992,
      "memory_usage": 0,
      "cpu_usage": 0.0,
      "success": true,
      "error_message": null,
      "cache_hit": false,
      "parallel_workers": 1,
      "parallel_efficiency": 1.0,
      "workload_balance": 1.0
    }
  ]
}